Workbook

Sheet Analysis

Sheet Dashboard
B1: URBANCART BUSINESS INTELLIGENCE DASHBOARD
B4: TOTAL SALES | D4: TOTAL PROFIT | F4: PROFIT MARGIN | H4: DELIVERED ORDERS | J4: RETURN RATE
B5: =SUM(Orders!R:R) -> 6861477.5 | D5: =SUM(Orders!S:S) -> 1633969.5 | F5: =IFERROR(D5/B5,0) -> 0.23813668 | H5: =COUNTIF(Orders!I:I,"Delivered") -> 2028 | J5: =IFERROR((COUNTA(Returns!A:A)-1)/H5,0) -> 0.11982249
B15: MONTHLY SALES & PROFIT TREND
A16: MONTH | B16: NET SALES | C16: NET PROFIT
A17: 45292 | B17: 251752.7 | C17: 56162.7
A18: 45323 | B18: 274152 | C18: 67120
A19: 45352 | B19: 404205.1 | C19: 106602.1
A20: 45383 | B20: 311656.95 | C20: 55784.95
A21: 45413 | B21: 393232.9 | C21: 102480.9
A22: 45444 | B22: 286552.5 | C22: 67320.5
A23: 45474 | B23: 367106.9 | C23: 95017.9
A24: 45505 | B24: 305441.85 | C24: 78222.85
A25: 45536 | B25: 228308.15 | C25: 53126.15
A26: 45566 | B26: 208410.5 | C26: 54370.5
A27: 45597 | B27: 303135.5 | C27: 73024.5
A28: 45627 | B28: 324314.65 | C28: 82964.65
... A38: 45931 | B38: 223380.6 | C38: 46740.6
A39: Grand Total | B39: 6861477.5 | C39: 1633969.5
O51: KEY BUSINESS INSIGHTS
B54: CATEGORY PERFORMANCE | O54: 1. Electronics is the primary revenue driver Electronics generated ₹15.25L sales and ₹4.17L profit, leading all categories in both revenue and absolute profit. Its 27.4% margin indicates strong profitability alongside high sales volume.
A55: Row Labels | B55: Sum of Net_Sales | C55: Sum of Net_Profit
A56: Beauty & Personal Care | B56: 1137503.8 | C56: 312499.8
A57: Electronics | B57: 1525296 | C57: 417287 | O57: 2. Organic is the strongest acquisition channel Organic generated ₹20.50L sales and ₹5.07L profit, contributing approximately 30% of total net sales. Maintaining strong SEO and organic visibility can support sustainable customer acquisition.
A58: Fashion | B58: 1384821.6 | C58: 263205.55
A59: Home & Kitchen | B59: 1316080.8 | C59: 321981.75
A60: Sports & Fitness | B60: 1497775.4 | C60: 318995.4 | O60: 3. High sales do not always mean highest profit Dumbbells generated the highest product sales at ₹5.62L, while Power Bank generated the highest profit at ₹1.53L. Product decisions should therefore consider both sales volume and profit contribution.
A61: Grand Total | B61: 6861477.5 | C61: 1633969.5
O63: 4. Returns are creating a significant financial impact UrbanCart recorded 243 returns and ₹8.42L in refunds, with an 11.98% return rate. Size/Fit Issues and Damaged Products together generated approximately ₹3.61L in refunds.
O66: 5. Fashion has a margin improvement opportunity Fashion generated ₹13.85L sales, but its 19.0% margin is below Electronics and Beauty & Personal Care. Pricing, discounting and product costs should be reviewed.
O69: 6. Product prioritisation should consider profitability Power Bank delivers approximately 29.0% margin, compared with around 15.0% for Jacket and 15.8% for Running Shoes. Higher-margin products can receive greater promotional focus.
O72: 7. Monthly performance shows significant volatility June 2025 recorded the highest monthly sales of ₹4.25L and profit of ₹1.02L, while October 2025 declined to ₹2.23L sales. Demand and campaign planning should account for these fluctuations.
B74: MARKETING PERFORMANCE
A75: Row Labels | B75: Sum of Net_Sales | C75: Sum of Net_Profit
A76: Affiliate | B76: 778871.85 | C76: 182874.85 | Q76: MANAGEMENT TAKEAWAY
A77: Email | B77: 713332.3 | C77: 173858.3 | O77: UrbanCart generates a healthy 23.81% overall profit margin, with clear opportunities to improve performance through high-margin products, strong organic acquisition, lower return-related losses and better category-level margin management.
A78: Facebook | B78: 871844.75 | C78: 205565.75
A79: Google Ads | B79: 1364648.2 | C79: 325969.2
A80: Instagram | B80: 1083179.5 | C80: 238202.5
A81: Organic | B81: 2049600.9 | C81: 507498.9
A82: Grand Total | B82: 6861477.5 | C82: 1633969.5 | O82: BUSINESS RECOMMENDATIONS
O85: 1. Scale high-performing categories Prioritise Electronics and other high-margin categories in promotions and inventory planning while maintaining healthy product-level margins.
O88: 2. Strengthen organic acquisition Continue investing in SEO, content and organic visibility because Organic currently contributes the highest sales and profit among marketing channels.
B89: TOP PRODUCTS
A90: Row Labels | B90: Sum of Net_Sales | C90: Sum of Net_Profit
A91: Air Fryer | B91: 361114.75 | C91: 90722.75 | O91: 3. Reduce return-related losses Investigate Size/Fit and Damaged Product returns through better product information, sizing guidance, packaging quality and quality checks.
A92: Dumbbells | B92: 562056.75 | C92: 121143.75
A93: Headphones | B93: 360329.6 | C93: 73986.6
A94: Jacket | B94: 385846.8 | C94: 57884.8 | O94: 4. Improve low-margin products Review pricing, discounts, supplier costs and product mix for lower-margin products such as Jacket and Running Shoes before increasing their sales aggressively.
A95: Perfume | B95: 445953.4 | C95: 110398.4
A96: Power Bank | B96: 528126.85 | C96: 153306.85
A97: Running Shoes | B97: 416659.75 | C97: 65852.75 | O97: 5. Prioritise profitable products Use product-level profit margins alongside sales volume when deciding which products should receive promotional and inventory priority.
A98: Smartphone | B98: 317824.2 | C98: 115833.2
A99: Sneakers | B99: 330195.05 | C99: 62434.05
A100: T-Shirt | B100: 358389.95 | C100: 70558.95 | O100: 6. Plan around monthly demand fluctuations Use historical monthly performance to improve campaign timing, inventory planning and sales forecasting, particularly around high- and low-demand periods.
A101: Grand Total | B101: 4066497.1 | C101: 922122.1
B106: RETURN ANALYSIS
A107: Row Labels | B107: Sum of Refund_Amount | C107: Count of Return_ID
A108: Changed Mind | B108: 106201.23 | C108: 21
A109: Damaged Product | B109: 179469.95 | C109: 49
A110: Not as Expected | B110: 102754.31 | C110: 46
A111: Quality Issue | B111: 154613.81 | C111: 41
A112: Size/Fit Issue | B112: 181111.66 | C112: 48
A113: Wrong Product | B113: 117423.21 | C113: 38
A114: Grand Total | B114: 841574.17 | C114: 243
A133: Customer Type | B133: Net Sales | C133: Net Profit
A134: Returning | B134: 4025595.9 | C134: 968551.85
A135: New | B135: 2835881.6 | C135: 665417.65
A147: Delivery Status | B147: Order Count
A148: Delivered | B148: 1306
A149: Delayed | B149: 722
A150: Cancelled | B150: 472 | R150: Delivery Partner | S150: Delayed Orders
R151: Ecom Express | S151: 155
R152: Shiprocket | S152: 118
R153: Delhivery | S153: 194
R154: XpressBees | S154: 112
R155: BlueDart | S155: 143

Sheet Orders
A1: Order_ID | B1: Order_Date | C1: Customer_ID | D1: Product_ID | E1: Quantity | F1: Unit_Price | G1: Discount | H1: Payment_Method | I1: Order_Status | J1: Delivery_Status | K1: Marketing_Channel | L1: Shipping_Cost | M1: Product_Cost | N1: Sales | O1: Product_Cost_Total | P1: Gross_Profit | Q1: Profit_Margin | R1: Net_Sales | S1: Net_Profit | T1: Month | U1: Order_Month | V1: Month_Start | W1: Category | X1: Product_Name
A2: ORD00001 | B2: 45711 | C2: CUST0608 | D2: P027 | E2: 3 | F2: 299 | G2: 0 | H2: Credit Card | I2: Delivered | J2: Delivered | K2: Affiliate | L2: 70 | M2: 206 | N2: =E2*F2-G2 -> 897 | O2: =E2*M2 -> 618 | P2: =N2-O2 -> 279 | Q2: =IFERROR(P2/N2,0) -> 0.31103679 | R2: =IF(I2="Cancelled",0,N2) -> 897 | S2: =IF(I2="Cancelled",0,P2) -> 279 | T2: =TEXT(B2,"mmm") -> Feb | U2: =TEXT(B2,"mmm-yyyy") -> Feb-2025 | V2: =DATE(YEAR(B2),MONTH(B2),1) -> 45689 | W2: =VLOOKUP(D2,Products!A:G,3,FALSE) -> Fashion | X2: =VLOOKUP(D2,Products!A:G,2,FALSE) -> Jeans
A3: ORD00002 | B3: 45465 | C3: CUST0206 | D3: P093 | E3: 4 | F3: 999 | G3: 599.4 | H3: UPI | I3: Delivered | J3: Delivered | K3: Affiliate | L3: 70 | M3: 629 | N3: =E3*F3-G3 -> 3396.6 | O3: =E3*M3 -> 2516 | P3: =N3-O3 -> 880.6 | Q3: =IFERROR(P3/N3,0) -> 0.25925926 | R3: =IF(I3="Cancelled",0,N3) -> 3396.6 | S3: =IF(I3="Cancelled",0,P3) -> 880.6 | T3: =TEXT(B3,"mmm") -> Jun | U3: =TEXT(B3,"mmm-yyyy") -> Jun-2024 | V3: =DATE(YEAR(B3),MONTH(B3),1) -> 45444 | W3: =VLOOKUP(D3,Products!A:G,3,FALSE) -> Sports & Fitness | X3: =VLOOKUP(D3,Products!A:G,2,FALSE) -> Fitness Band
A4: ORD00003 | B4: 45863 | C4: CUST1126 | D4: P071 | E4: 1 | F4: 999 | G4: 49.95 | H4: UPI | I4: Delivered | J4: Delivered | K4: Instagram | L4: 40 | M4: 818 | N4: =E4*F4-G4 -> 949.05 | O4: =E4*M4 -> 818 | P4: =N4-O4 -> 131.05 | Q4: =IFERROR(P4/N4,0) -> 0.13808545 | R4: =IF(I4="Cancelled",0,N4) -> 949.05 | S4: =IF(I4="Cancelled",0,P4) -> 131.05 | T4: =TEXT(B4,"mmm") -> Jul | U4: =TEXT(B4,"mmm-yyyy") -> Jul-2025 | V4: =DATE(YEAR(B4),MONTH(B4),1) -> 45839 | W4: =VLOOKUP(D4,Products!A:G,3,FALSE) -> Beauty & Personal Care | X4: =VLOOKUP(D4,Products!A:G,2,FALSE) -> Trimmer
A5: ORD00004 | B5: 45388 | C5: CUST0351 | D5: P089 | E5: 1 | F5: 2999 | G5: 149.95 | H5: UPI | I5: Delivered | J5: Delayed | K5: Google Ads | L5: 100 | M5: 2453 | N5: =E5*F5-G5 -> 2849.05 | O5: =E5*M5 -> 2453 | P5: =N5-O5 -> 396.05 | Q5: =IFERROR(P5/N5,0) -> 0.13901125 | R5: =IF(I5="Cancelled",0,N5) -> 2849.05 | S5: =IF(I5="Cancelled",0,P5) -> 396.05 | T5: =TEXT(B5,"mmm") -> Apr | U5: =TEXT(B5,"mmm-yyyy") -> Apr-2024 | V5: =DATE(YEAR(B5),MONTH(B5),1) -> 45383 | W5: =VLOOKUP(D5,Products!A:G,3,FALSE) -> Sports & Fitness | X5: =VLOOKUP(D5,Products!A:G,2,FALSE) -> Dumbbells
A6: ORD00005 | B6: 45376 | C6: CUST0120 | D6: P092 | E6: 2 | F6: 999 | G6: 299.7 | H6: Net Banking | I6: Delivered | J6: Delivered | K6: Organic | L6: 100 | M6: 727 | N6: =E6*F6-G6 -> 1698.3 | O6: =E6*M6 -> 1454 | P6: =N6-O6 -> 244.3 | Q6: =IFERROR(P6/N6,0) -> 0.14384973 | R6: =IF(I6="Cancelled",0,N6) -> 1698.3 | S6: =IF(I6="Cancelled",0,P6) -> 244.3 | T6: =TEXT(B6,"mmm") -> Mar | U6: =TEXT(B6,"mmm-yyyy") -> Mar-2024 | V6: =DATE(YEAR(B6),MONTH(B6),1) -> 45352 | W6: =VLOOKUP(D6,Products!A:G,3,FALSE) -> Sports & Fitness | X6: =VLOOKUP(D6,Products!A:G,2,FALSE) -> Dumbbells
A7: ORD00006 | B7: 45412 | C7: CUST0312 | D7: P041 | E7: 1 | F7: 399 | G7: 0 | H7: Credit Card | I7: Cancelled | J7: Cancelled | K7: Google Ads | L7: 40 | M7: 315 | N7: =E7*F7-G7 -> 399 | O7: =E7*M7 -> 315 | P7: =N7-O7 -> 84 | Q7: =IFERROR(P7/N7,0) -> 0.21052632 | R7: =IF(I7="Cancelled",0,N7) -> 0 | S7: =IF(I7="Cancelled",0,P7) -> 0 | T7: =TEXT(B7,"mmm") -> Apr | U7: =TEXT(B7,"mmm-yyyy") -> Apr-2024 | V7: =DATE(YEAR(B7),MONTH(B7),1) -> 45383 | W7: =VLOOKUP(D7,Products!A:G,3,FALSE) -> Home & Kitchen | X7: =VLOOKUP(D7,Products!A:G,2,FALSE) -> Mixer Grinder
A8: ORD00007 | B8: 45443 | C8: CUST1021 | D8: P004 | E8: 1 | F8: 8999 | G8: 1799.8 | H8: UPI | I8: Delivered | J8: Delivered | K8: Facebook | L8: 70 | M8: 5059 | N8: =E8*F8-G8 -> 7199.2 | O8: =E8*M8 -> 5059 | P8: =N8-O8 -> 2140.2 | Q8: =IFERROR(P8/N8,0) -> 0.29728303 | R8: =IF(I8="Cancelled",0,N8) -> 7199.2 | S8: =IF(I8="Cancelled",0,P8) -> 2140.2 | T8: =TEXT(B8,"mmm") -> May | U8: =TEXT(B8,"mmm-yyyy") -> May-2024 | V8: =DATE(YEAR(B8),MONTH(B8),1) -> 45413 | W8: =VLOOKUP(D8,Products!A:G,3,FALSE) -> Electronics | X8: =VLOOKUP(D8,Products!A:G,2,FALSE) -> Smartphone
A9: ORD00008 | B9: 45603 | C9: CUST0763 | D9: P014 | E9: 1 | F9: 2499 | G9: 0 | H9: Credit Card | I9: Cancelled | J9: Cancelled | K9: Email | L9: 100 | M9: 1599 | N9: =E9*F9-G9 -> 2499 | O9: =E9*M9 -> 1599 | P9: =N9-O9 -> 900 | Q9: =IFERROR(P9/N9,0) -> 0.36014406 | R9: =IF(I9="Cancelled",0,N9) -> 0 | S9: =IF(I9="Cancelled",0,P9) -> 0 | T9: =TEXT(B9,"mmm") -> Nov | U9: =TEXT(B9,"mmm-yyyy") -> Nov-2024 | V9: =DATE(YEAR(B9),MONTH(B9),1) -> 45597 | W9: =VLOOKUP(D9,Products!A:G,3,FALSE) -> Electronics | X9: =VLOOKUP(D9,Products!A:G,2,FALSE) -> Smartwatch
A10: ORD00009 | B10: 45765 | C10: CUST0720 | D10: P077 | E10: 1 | F10: 3999 | G10: 999.75 | H10: Cash on Delivery | I10: Delivered | J10: Delivered | K10: Instagram | L10: 40 | M10: 2547 | N10: =E10*F10-G10 -> 2999.25 | O10: =E10*M10 -> 2547 | P10: =N10-O10 -> 452.25 | Q10: =IFERROR(P10/N10,0) -> 0.1507877 | R10: =IF(I10="Cancelled",0,N10) -> 2999.25 | S10: =IF(I10="Cancelled",0,P10) -> 452.25 | T10: =TEXT(B10,"mmm") -> Apr | U10: =TEXT(B10,"mmm-yyyy") -> Apr-2025 | V10: =DATE(YEAR(B10),MONTH(B10),1) -> 45748 | W10: =VLOOKUP(D10,Products!A:G,3,FALSE) -> Beauty & Personal Care | X10: =VLOOKUP(D10,Products!A:G,2,FALSE) -> Perfume
A11: ORD00010 | B11: 45871 | C11: CUST0512 | D11: P037 | E11: 4 | F11: 399 | G11: 0 | H11: Debit Card | I11: Delivered | J11: Delayed | K11: Google Ads | L11: 80 | M11: 226 | N11: =E11*F11-G11 -> 1596 | O11: =E11*M11 -> 904 | P11: =N11-O11 -> 692 | Q11: =IFERROR(P11/N11,0) -> 0.43358396 | R11: =IF(I11="Cancelled",0,N11) -> 1596 | S11: =IF(I11="Cancelled",0,P11) -> 692 | T11: =TEXT(B11,"mmm") -> Aug | U11: =TEXT(B11,"mmm-yyyy") -> Aug-2025 | V11: =DATE(YEAR(B11),MONTH(B11),1) -> 45870 | W11: =VLOOKUP(D11,Products!A:G,3,FALSE) -> Fashion | X11: =VLOOKUP(D11,Products!A:G,2,FALSE) -> Backpack
A12: ORD00011 | B12: 45519 | C12: CUST0744 | D12: P017 | E12: 4 | F12: 6999 | G12: 4199.4 | H12: Net Banking | I12: Delivered | J12: Delivered | K12: Organic | L12: 70 | M12: 4046 | N12: =E12*F12-G12 -> 23796.6 | O12: =E12*M12 -> 16184 | P12: =N12-O12 -> 7612.6 | Q12: =IFERROR(P12/N12,0) -> 0.31990284 | R12: =IF(I12="Cancelled",0,N12) -> 23796.6 | S12: =IF(I12="Cancelled",0,P12) -> 7612.6 | T12: =TEXT(B12,"mmm") -> Aug | U12: =TEXT(B12,"mmm-yyyy") -> Aug-2024 | V12: =DATE(YEAR(B12),MONTH(B12),1) -> 45505 | W12: =VLOOKUP(D12,Products!A:G,3,FALSE) -> Electronics | X12: =VLOOKUP(D12,Products!A:G,2,FALSE) -> Power Bank
A13: ORD00012 | B13: 45401 | C13: CUST0456 | D13: P084 | E13: 1 | F13: 999 | G13: 49.95 | H13: UPI | I13: Delivered | J13: Delivered | K13: Affiliate | L13: 100 | M13: 809 | N13: =E13*F13-G13 -> 949.05 | O13: =E13*M13 -> 809 | P13: =N13-O13 -> 140.05 | Q13: =IFERROR(P13/N13,0) -> 0.14756862 | R13: =IF(I13="Cancelled",0,N13) -> 949.05 | S13: =IF(I13="Cancelled",0,P13) -> 140.05 | T13: =TEXT(B13,"mmm") -> Apr | U13: =TEXT(B13,"mmm-yyyy") -> Apr-2024 | V13: =DATE(YEAR(B13),MONTH(B13),1) -> 45383 | W13: =VLOOKUP(D13,Products!A:G,3,FALSE) -> Sports & Fitness | X13: =VLOOKUP(D13,Products!A:G,2,FALSE) -> Yoga Mat
... A2501: ORD02500 | B2501: 45392 | C2501: CUST1120 | D2501: P071 | E2501: 1 | F2501: 999 | G2501: 0 | H2501: UPI | I2501: Cancelled | J2501: Cancelled | K2501: Google Ads | L2501: 60 | M2501: 818 | N2501: =E2501*F2501-G2501 -> 999 | O2501: =E2501*M2501 -> 818 | P2501: =N2501-O2501 -> 181 | Q2501: =IFERROR(P2501/N2501,0) -> 0.18118118 | R2501: =IF(I2501="Cancelled",0,N2501) -> 0 | S2501: =IF(I2501="Cancelled",0,P2501) -> 0 | T2501: =TEXT(B2501,"mmm") -> Apr | U2501: =TEXT(B2501,"mmm-yyyy") -> Apr-2024 | V2501: =DATE(YEAR(B2501),MONTH(B2501),1) -> 45383 | W2501: =VLOOKUP(D2501,Products!A:G,3,FALSE) -> Beauty & Personal Care | X2501: =VLOOKUP(D2501,Products!A:G,2,FALSE) -> Trimmer

Sheet Customers
A1: Customer_ID | B1: Customer_Name | C1: Age | D1: Gender | E1: City | F1: State | G1: Registration_Date | H1: Customer_Type
A2: CUST0001 | B2: Karan Gupta | C2: 53 | D2: Male | E2: Ahmedabad | F2: Gujarat | G2: 45600 | H2: New
A3: CUST0002 | B3: Saurabh Jain | C3: 35 | D3: Male | E3: Nagpur | F3: Maharashtra | G3: 45829 | H3: Returning
A4: CUST0003 | B4: Ankit Shah | C4: 54 | D4: Male | E4: Bhopal | F4: Madhya Pradesh | G4: 45305 | H4: Returning
A5: CUST0004 | B5: Isha Patel | C5: 36 | D5: Male | E5: Guwahati | F5: Assam | G5: 45665 | H5: New
A6: CUST0005 | B6: Nandini Verma | C6: 45 | D6: Female | E6: Lucknow | F6: Uttar Pradesh | G6: 45848 | H6: New
A7: CUST0006 | B7: Simran Jain | C7: 57 | D7: Female | E7: Bhopal | F7: Madhya Pradesh | G7: 45719 | H7: New
A8: CUST0007 | B8: Utkarsh Kumar | C8: 37 | D8: Male | E8: Jaipur | F8: Rajasthan | G8: 45524 | H8: New
A9: CUST0008 | B9: Isha Gupta | C9: 50 | D9: Male | E9: Bengaluru | F9: Karnataka | G9: 45854 | H9: Returning
A10: CUST0009 | B10: Ankit Kumar | C10: 29 | D10: Male | E10: Lucknow | F10: Uttar Pradesh | G10: 45954 | H10: Returning
A11: CUST0010 | B11: Aditya Yadav | C11: 32 | D11: Female | E11: Prayagraj | F11: Uttar Pradesh | G11: 45731 | H11: New
A12: CUST0011 | B12: Isha Singh | C12: 58 | D12: Female | E12: Delhi | F12: Delhi | G12: 45793 | H12: Returning
A13: CUST0012 | B13: Kavya Mehta | C13: 56 | D13: Male | E13: Delhi | F13: Delhi | G13: 45566 | H13: Returning
... A1201: CUST1200 | B1201: Riya Mehta | C1201: 60 | D1201: Female | E1201: Varanasi | F1201: Uttar Pradesh | G1201: 45843 | H1201: New

Sheet Products
A1: Product_ID | B1: Product_Name | C1: Category | D1: Sub_Category | E1: Brand | F1: Selling_Price | G1: Product_Cost
A2: P001 | B2: Smartphone | C2: Electronics | D2: Smartphone | E2: UrbanX | F2: 799 | G2: 547
A3: P002 | B3: Smartphone | C3: Electronics | D3: Smartphone | E3: Prime | F3: 999 | G3: 590
A4: P003 | B4: Smartphone | C4: Electronics | D4: Smartphone | E4: Vistara | F4: 399 | G4: 307
A5: P004 | B5: Smartphone | C5: Electronics | D5: Smartphone | E5: Nova | F5: 8999 | G5: 5059
A6: P005 | B6: Laptop | C6: Electronics | D6: Laptop | E6: Luma | F6: 599 | G6: 426
A7: P006 | B7: Laptop | C7: Electronics | D7: Laptop | E7: Vistara | F7: 399 | G7: 221
A8: P007 | B8: Laptop | C8: Electronics | D8: Laptop | E8: Aero | F8: 599 | G8: 470
A9: P008 | B9: Laptop | C9: Electronics | D9: Laptop | E9: Crest | F9: 299 | G9: 197
A10: P009 | B10: Headphones | C10: Electronics | D10: Headphones | E10: Nova | F10: 4999 | G10: 2853
A11: P010 | B11: Headphones | C11: Electronics | D11: Headphones | E11: Aero | F11: 2499 | G11: 2030
A12: P011 | B12: Headphones | C12: Electronics | D12: Headphones | E12: Luma | F12: 799 | G12: 645
A13: P012 | B13: Headphones | C13: Electronics | D13: Headphones | E13: Crest | F13: 1599 | G13: 1169
... A101: P100 | B101: Cricket Bat | C101: Sports & Fitness | D101: Cricket Bat | E101: Crest | F101: 4999 | G101: 3463

Sheet Order_Items
A1: Order_Item_ID | B1: Order_ID | C1: Product_ID | D1: Quantity | E1: Unit_Price | F1: Discount | G1: Total_Sales | H1: Product_Cost | I1: Profit | J1: Data_Check | K1: Profit_Check
A2: OI000001 | B2: ORD00001 | C2: P027 | D2: 3 | E2: 299 | F2: 0 | G2: =IFERROR(D2*E2-F2,0) -> 897 | H2: 206 | I2: =G2-(D2*H2) -> 279 | J2: =IF(AND(COUNTIF(Products!A:A,C2)=1,E2=VLOOKUP(C2,Products!A:G,6,FALSE),H2=VLOOKUP(C2,Products!A:G,7,FALSE)),"OK","ERROR") -> OK | K2: =IF(I2=G2-(D2*H2),"OK","ERROR") -> OK
A3: OI000002 | B3: ORD00002 | C3: P093 | D3: 4 | E3: 999 | F3: 599.4 | G3: =IFERROR(D3*E3-F3,0) -> 3396.6 | H3: 629 | I3: =G3-(D3*H3) -> 880.6 | J3: =IF(AND(COUNTIF(Products!A:A,C3)=1,E3=VLOOKUP(C3,Products!A:G,6,FALSE),H3=VLOOKUP(C3,Products!A:G,7,FALSE)),"OK","ERROR") -> OK | K3: =IF(I3=G3-(D3*H3),"OK","ERROR") -> OK
A4: OI000003 | B4: ORD00003 | C4: P071 | D4: 1 | E4: 999 | F4: 49.95 | G4: =IFERROR(D4*E4-F4,0) -> 949.05 | H4: 818 | I4: =G4-(D4*H4) -> 131.05 | J4: =IF(AND(COUNTIF(Products!A:A,C4)=1,E4=VLOOKUP(C4,Products!A:G,6,FALSE),H4=VLOOKUP(C4,Products!A:G,7,FALSE)),"OK","ERROR") -> OK | K4: =IF(I4=G4-(D4*H4),"OK","ERROR") -> OK
A5: OI000004 | B5: ORD00004 | C5: P089 | D5: 1 | E5: 2999 | F5: 149.95 | G5: =IFERROR(D5*E5-F5,0) -> 2849.05 | H5: 2453 | I5: =G5-(D5*H5) -> 396.05 | J5: =IF(AND(COUNTIF(Products!A:A,C5)=1,E5=VLOOKUP(C5,Products!A:G,6,FALSE),H5=VLOOKUP(C5,Products!A:G,7,FALSE)),"OK","ERROR") -> OK | K5: =IF(I5=G5-(D5*H5),"OK","ERROR") -> OK
A6: OI000005 | B6: ORD00005 | C6: P092 | D6: 2 | E6: 999 | F6: 299.7 | G6: =IFERROR(D6*E6-F6,0) -> 1698.3 | H6: 727 | I6: =G6-(D6*H6) -> 244.3 | J6: =IF(AND(COUNTIF(Products!A:A,C6)=1,E6=VLOOKUP(C6,Products!A:G,6,FALSE),H6=VLOOKUP(C6,Products!A:G,7,FALSE)),"OK","ERROR") -> OK | K6: =IF(I6=G6-(D6*H6),"OK","ERROR") -> OK
A7: OI000006 | B7: ORD00006 | C7: P041 | D7: 1 | E7: 399 | F7: 0 | G7: =IFERROR(D7*E7-F7,0) -> 399 | H7: 315 | I7: =G7-(D7*H7) -> 84 | J7: =IF(AND(COUNTIF(Products!A:A,C7)=1,E7=VLOOKUP(C7,Products!A:G,6,FALSE),H7=VLOOKUP(C7,Products!A:G,7,FALSE)),"OK","ERROR") -> OK | K7: =IF(I7=G7-(D7*H7),"OK","ERROR") -> OK
A8: OI000007 | B8: ORD00007 | C8: P004 | D8: 1 | E8: 8999 | F8: 1799.8 | G8: =IFERROR(D8*E8-F8,0) -> 7199.2 | H8: 5059 | I8: =G8-(D8*H8) -> 2140.2 | J8: =IF(AND(COUNTIF(Products!A:A,C8)=1,E8=VLOOKUP(C8,Products!A:G,6,FALSE),H8=VLOOKUP(C8,Products!A:G,7,FALSE)),"OK","ERROR") -> OK | K8: =IF(I8=G8-(D8*H8),"OK","ERROR") -> OK
A9: OI000008 | B9: ORD00008 | C9: P014 | D9: 1 | E9: 2499 | F9: 0 | G9: =IFERROR(D9*E9-F9,0) -> 2499 | H9: 1599 | I9: =G9-(D9*H9) -> 900 | J9: =IF(AND(COUNTIF(Products!A:A,C9)=1,E9=VLOOKUP(C9,Products!A:G,6,FALSE),H9=VLOOKUP(C9,Products!A:G,7,FALSE)),"OK","ERROR") -> OK | K9: =IF(I9=G9-(D9*H9),"OK","ERROR") -> OK
A10: OI000009 | B10: ORD00009 | C10: P077 | D10: 1 | E10: 3999 | F10: 999.75 | G10: =IFERROR(D10*E10-F10,0) -> 2999.25 | H10: 2547 | I10: =G10-(D10*H10) -> 452.25 | J10: =IF(AND(COUNTIF(Products!A:A,C10)=1,E10=VLOOKUP(C10,Products!A:G,6,FALSE),H10=VLOOKUP(C10,Products!A:G,7,FALSE)),"OK","ERROR") -> OK | K10: =IF(I10=G10-(D10*H10),"OK","ERROR") -> OK
A11: OI000010 | B11: ORD00010 | C11: P037 | D11: 4 | E11: 399 | F11: 0 | G11: =IFERROR(D11*E11-F11,0) -> 1596 | H11: 226 | I11: =G11-(D11*H11) -> 692 | J11: =IF(AND(COUNTIF(Products!A:A,C11)=1,E11=VLOOKUP(C11,Products!A:G,6,FALSE),H11=VLOOKUP(C11,Products!A:G,7,FALSE)),"OK","ERROR") -> OK | K11: =IF(I11=G11-(D11*H11),"OK","ERROR") -> OK
A12: OI000011 | B12: ORD00011 | C12: P017 | D12: 4 | E12: 6999 | F12: 4199.4 | G12: =IFERROR(D12*E12-F12,0) -> 23796.6 | H12: 4046 | I12: =G12-(D12*H12) -> 7612.6 | J12: =IF(AND(COUNTIF(Products!A:A,C12)=1,E12=VLOOKUP(C12,Products!A:G,6,FALSE),H12=VLOOKUP(C12,Products!A:G,7,FALSE)),"OK","ERROR") -> OK | K12: =IF(I12=G12-(D12*H12),"OK","ERROR") -> OK
A13: OI000012 | B13: ORD00012 | C13: P084 | D13: 1 | E13: 999 | F13: 49.95 | G13: =IFERROR(D13*E13-F13,0) -> 949.05 | H13: 809 | I13: =G13-(D13*H13) -> 140.05 | J13: =IF(AND(COUNTIF(Products!A:A,C13)=1,E13=VLOOKUP(C13,Products!A:G,6,FALSE),H13=VLOOKUP(C13,Products!A:G,7,FALSE)),"OK","ERROR") -> OK | K13: =IF(I13=G13-(D13*H13),"OK","ERROR") -> OK
... A2501: OI002500 | B2501: ORD02500 | C2501: P071 | D2501: 1 | E2501: 999 | F2501: 0 | G2501: =IFERROR(D2501*E2501-F2501,0) -> 999 | H2501: 818 | I2501: =G2501-(D2501*H2501) -> 181 | J2501: =IF(AND(COUNTIF(Products!A:A,C2501)=1,E2501=VLOOKUP(C2501,Products!A:G,6,FALSE),H2501=VLOOKUP(C2501,Products!A:G,7,FALSE)),"OK","ERROR") -> OK | K2501: =IF(I2501=G2501-(D2501*H2501),"OK","ERROR") -> OK

Sheet Payments
A1: Payment_ID | B1: Order_ID | C1: Payment_Date | D1: Payment_Method | E1: Amount | F1: Payment_Status
A2: PAY00001 | B2: ORD00001 | C2: 45711 | D2: Credit Card | E2: 897 | F2: Paid
A3: PAY00002 | B3: ORD00002 | C3: 45465 | D3: UPI | E3: 3396.6 | F3: Paid
A4: PAY00003 | B4: ORD00003 | C4: 45863 | D4: UPI | E4: 949.05 | F4: Paid
A5: PAY00004 | B5: ORD00004 | C5: 45388 | D5: UPI | E5: 2849.05 | F5: Paid
A6: PAY00005 | B6: ORD00005 | C6: 45376 | D6: Net Banking | E6: 1698.3 | F6: Paid
A7: PAY00006 | B7: ORD00006 | C7: 45412 | D7: Credit Card | E7: 399 | F7: Failed
A8: PAY00007 | B8: ORD00007 | C8: 45443 | D8: UPI | E8: 7199.2 | F8: Paid
A9: PAY00008 | B9: ORD00008 | C9: 45603 | D9: Credit Card | E9: 2499 | F9: Failed
A10: PAY00009 | B10: ORD00009 | C10: 45765 | D10: Cash on Delivery | E10: 2999.25 | F10: Paid
A11: PAY00010 | B11: ORD00010 | C11: 45871 | D11: Debit Card | E11: 1596 | F11: Paid
A12: PAY00011 | B12: ORD00011 | C12: 45519 | D12: Net Banking | E12: 23796.6 | F12: Paid
A13: PAY00012 | B13: ORD00012 | C13: 45401 | D13: UPI | E13: 949.05 | F13: Paid
... A2501: PAY02500 | B2501: ORD02500 | C2501: 45392 | D2501: UPI | E2501: 999 | F2501: Failed

Sheet Returns
A1: Return_ID | B1: Order_ID | C1: Product_ID | D1: Return_Date | E1: Return_Reason | F1: Refund_Amount | G1: Return_Status
A2: RET0001 | B2: ORD00353 | C2: P088 | D2: 45563 | E2: Not as Expected | F2: 2651.53 | G2: Approved
A3: RET0002 | B3: ORD01201 | C3: P029 | D3: 45739 | E3: Not as Expected | F3: 9524.14 | G3: Processed
A4: RET0003 | B4: ORD01149 | C4: P095 | D4: 45776 | E4: Changed Mind | F4: 295.22 | G4: Approved
A5: RET0004 | B5: ORD00460 | C5: P014 | D5: 45670 | E5: Damaged Product | F5: 4375.44 | G5: Approved
A6: RET0005 | B6: ORD01911 | C6: P063 | D6: 45491 | E6: Changed Mind | F6: 5242.75 | G6: Approved
A7: RET0006 | B7: ORD00064 | C7: P087 | D7: 45767 | E7: Size/Fit Issue | F7: 711.82 | G7: Approved
A8: RET0007 | B8: ORD00587 | C8: P057 | D8: 45729 | E8: Wrong Product | F8: 837.07 | G8: Approved
A9: RET0008 | B9: ORD00806 | C9: P070 | D9: 45509 | E9: Damaged Product | F9: 1483.3 | G9: Approved
A10: RET0009 | B10: ORD01760 | C10: P052 | D10: 45581 | E10: Not as Expected | F10: 1462.77 | G10: Approved
A11: RET0010 | B11: ORD01203 | C11: P028 | D11: 45364 | E11: Size/Fit Issue | F11: 2985.53 | G11: Approved
A12: RET0011 | B12: ORD00906 | C12: P053 | D12: 45513 | E12: Damaged Product | F12: 479.43 | G12: Approved
A13: RET0012 | B13: ORD00292 | C13: P075 | D13: 45822 | E13: Damaged Product | F13: 3333.31 | G13: Approved
... A244: RET0243 | B244: ORD02045 | C244: P081 | D244: 45618 | E244: Not as Expected | F244: 418.48 | G244: Approved

Sheet Delivery
A1: Delivery_ID | B1: Order_ID | C1: Dispatch_Date | D1: Expected_Delivery_Date | E1: Actual_Delivery_Date | F1: Delivery_Partner | G1: Delivery_Status | H1: Delivery_Cost
A2: DEL00001 | B2: ORD00001 | C2: 45711 | D2: 45713 | E2: 45713 | F2: Delhivery | G2: Delivered | H2: 55
A3: DEL00002 | B3: ORD00002 | C3: 45465 | D3: 45469 | E3: 45469 | F3: BlueDart | G3: Delivered | H3: 80
A4: DEL00003 | B4: ORD00003 | C4: 45864 | D4: 45868 | E4: 45869 | F4: Shiprocket | G4: Delayed | H4: 55
A5: DEL00004 | B5: ORD00004 | C5: 45388 | D5: 45392 | E5: 45392 | F5: Ecom Express | G5: Delivered | H5: 100
A6: DEL00005 | B6: ORD00005 | C6: 45377 | D6: 45381 | E6: 45382 | F6: Delhivery | G6: Delayed | H6: 70
A7: DEL00006 | B7: ORD00006 | C7: 45412 | D7: 45414 | F7: Ecom Express | G7: Cancelled | H7: 50
A8: DEL00007 | B8: ORD00007 | C8: 45443 | D8: 45447 | E8: 45447 | F8: Delhivery | G8: Delivered | H8: 45
A9: DEL00008 | B9: ORD00008 | C9: 45604 | D9: 45607 | F9: Shiprocket | G9: Cancelled | H9: 55
A10: DEL00009 | B10: ORD00009 | C10: 45765 | D10: 45769 | E10: 45772 | F10: Ecom Express | G10: Delayed | H10: 100
A11: DEL00010 | B11: ORD00010 | C11: 45872 | D11: 45875 | E11: 45877 | F11: Shiprocket | G11: Delayed | H11: 45
A12: DEL00011 | B12: ORD00011 | C12: 45520 | D12: 45525 | E12: 45526 | F12: BlueDart | G12: Delayed | H12: 100
A13: DEL00012 | B13: ORD00012 | C13: 45402 | D13: 45404 | E13: 45404 | F13: Delhivery | G13: Delivered | H13: 45
A14: DEL00013 | B14: ORD00013 | C14: 45905 | D14: 45908 | E14: 45908 | F14: Shiprocket | G14: Delivered | H14: 55
A15: DEL00014 | B15: ORD00014 | C15: 45793 | D15: 45796 | E15: 45796 | F15: Shiprocket | G15: Delivered | H15: 50
A16: DEL00015 | B16: ORD00015 | C16: 45349 | D16: 45352 | E16: 45354 | F16: Delhivery | G16: Delayed | H16: 100
A17: DEL00016 | B17: ORD00016 | C17: 45550 | D17: 45554 | E17: 45554 | F17: Shiprocket | G17: Delivered | H17: 45
A18: DEL00017 | B18: ORD00017 | C18: 45306 | D18: 45309 | F18: Delhivery | G18: Cancelled | H18: 50
A19: DEL00018 | B19: ORD00018 | C19: 45413 | D19: 45415 | E19: 45415 | F19: Delhivery | G19: Delivered | H19: 100
A20: DEL00019 | B20: ORD00019 | C20: 45652 | D20: 45656 | E20: 45656 | F20: XpressBees | G20: Delivered | H20: 45
A21: DEL00020 | B21: ORD00020 | C21: 45642 | D21: 45644 | E21: 45644 | F21: BlueDart | G21: Delivered | H21: 80
A22: DEL00021 | B22: ORD00021 | C22: 45631 | D22: 45636 | E22: 45637 | F22: Delhivery | G22: Delayed | H22: 100
A23: DEL00022 | B23: ORD00022 | C23: 45389 | D23: 45391 | E23: 45393 | F23: BlueDart | G23: Delayed | H23: 60
A24: DEL00023 | B24: ORD00023 | C24: 45623 | D24: 45625 | E24: 45625 | F24: Delhivery | G24: Delivered | H24: 70
A25: DEL00024 | B25: ORD00024 | C25: 45712 | D25: 45717 | E25: 45717 | F25: Shiprocket | G25: Delivered | H25: 80
A26: DEL00025 | B26: ORD00025 | C26: 45782 | D26: 45784 | E26: 45785 | F26: Shiprocket | G26: Delayed | H26: 45
A27: DEL00026 | B27: ORD00026 | C27: 45580 | D27: 45582 | E27: 45582 | F27: Ecom Express | G27: Delivered | H27: 55
A28: DEL00027 | B28: ORD00027 | C28: 45364 | D28: 45369 | E28: 45369 | F28: XpressBees | G28: Delivered | H28: 70
A29: DEL00028 | B29: ORD00028 | C29: 45769 | D29: 45773 | E29: 45773 | F29: Delhivery | G29: Delivered | H29: 60
A30: DEL00029 | B30: ORD00029 | C30: 45877 | D30: 45882 | E30: 45882 | F30: XpressBees | G30: Delivered | H30: 55
A31: DEL00030 | B31: ORD00030 | C31: 45622 | D31: 45625 | E31: 45625 | F31: BlueDart | G31: Delivered | H31: 70
A32: DEL00031 | B32: ORD00031 | C32: 45379 | D32: 45382 | F32: Ecom Express | G32: Cancelled | H32: 80
A33: DEL00032 | B33: ORD00032 | C33: 45437 | D33: 45439 | E33: 45439 | F33: XpressBees | G33: Delivered | H33: 45
A34: DEL00033 | B34: ORD00033 | C34: 45920 | D34: 45924 | E34: 45924 | F34: BlueDart | G34: Delivered | H34: 80
A35: DEL00034 | B35: ORD00034 | C35: 45621 | D35: 45624 | F35: XpressBees | G35: Cancelled | H35: 60
A36: DEL00035 | B36: ORD00035 | C36: 45727 | D36: 45729 | F36: BlueDart | G36: Cancelled | H36: 55
A37: DEL00036 | B37: ORD00036 | C37: 45854 | D37: 45858 | E37: 45858 | F37: Delhivery | G37: Delivered | H37: 50
A38: DEL00037 | B38: ORD00037 | C38: 45311 | D38: 45313 | F38: Delhivery | G38: Cancelled | H38: 45
A39: DEL00038 | B39: ORD00038 | C39: 45896 | D39: 45898 | E39: 45898 | F39: BlueDart | G39: Delivered | H39: 55
A40: DEL00039 | B40: ORD00039 | C40: 45577 | D40: 45582 | E40: 45583 | F40: BlueDart | G40: Delayed | H40: 80
A41: DEL00040 | B41: ORD00040 | C41: 45805 | D41: 45807 | E41: 45809 | F41: XpressBees | G41: Delayed | H41: 45
A42: DEL00041 | B42: ORD00041 | C42: 45867 | D42: 45872 | E42: 45872 | F42: XpressBees | G42: Delivered | H42: 45
A43: DEL00042 | B43: ORD00042 | C43: 45432 | D43: 45437 | F43: XpressBees | G43: Cancelled | H43: 55
A44: DEL00043 | B44: ORD00043 | C44: 45751 | D44: 45756 | E44: 45757 | F44: XpressBees | G44: Delayed | H44: 70
A45: DEL00044 | B45: ORD00044 | C45: 45871 | D45: 45874 | E45: 45874 | F45: Ecom Express | G45: Delivered | H45: 45
A46: DEL00045 | B46: ORD00045 | C46: 45604 | D46: 45607 | E46: 45607 | F46: Delhivery | G46: Delivered | H46: 45
A47: DEL00046 | B47: ORD00046 | C47: 45597 | D47: 45601 | F47: Ecom Express | G47: Cancelled | H47: 100
A48: DEL00047 | B48: ORD00047 | C48: 45813 | D48: 45815 | E48: 45815 | F48: XpressBees | G48: Delivered | H48: 50
A49: DEL00048 | B49: ORD00048 | C49: 45839 | D49: 45843 | E49: 45843 | F49: BlueDart | G49: Delivered | H49: 50
A50: DEL00049 | B50: ORD00049 | C50: 45815 | D50: 45819 | F50: Delhivery | G50: Cancelled | H50: 80
A51: DEL00050 | B51: ORD00050 | C51: 45920 | D51: 45924 | E51: 45925 | F51: XpressBees | G51: Delayed | H51: 45
A52: DEL00051 | B52: ORD00051 | C52: 45923 | D52: 45927 | E52: 45927 | F52: Delhivery | G52: Delivered | H52: 80
A53: DEL00052 | B53: ORD00052 | C53: 45858 | D53: 45862 | E53: 45862 | F53: Shiprocket | G53: Delivered | H53: 50
A54: DEL00053 | B54: ORD00053 | C54: 45825 | D54: 45829 | F54: Delhivery | G54: Cancelled | H54: 70
A55: DEL00054 | B55: ORD00054 | C55: 45783 | D55: 45788 | E55: 45788 | F55: Shiprocket | G55: Delivered | H55: 60
A56: DEL00055 | B56: ORD00055 | C56: 45754 | D56: 45758 | E56: 45758 | F56: Delhivery | G56: Delivered | H56: 45
A57: DEL00056 | B57: ORD00056 | C57: 45607 | D57: 45609 | E57: 45609 | F57: Ecom Express | G57: Delivered | H57: 100
A58: DEL00057 | B58: ORD00057 | C58: 45666 | D58: 45671 | E58: 45673 | F58: BlueDart | G58: Delayed | H58: 80
A59: DEL00058 | B59: ORD00058 | C59: 45502 | D59: 45506 | E59: 45506 | F59: Delhivery | G59: Delivered | H59: 55
A60: DEL00059 | B60: ORD00059 | C60: 45928 | D60: 45931 | E60: 45933 | F60: Ecom Express | G60: Delayed | H60: 100
A61: DEL00060 | B61: ORD00060 | C61: 45528 | D61: 45533 | F61: Ecom Express | G61: Cancelled | H61: 100
A62: DEL00061 | B62: ORD00061 | C62: 45692 | D62: 45694 | E62: 45694 | F62: Delhivery | G62: Delivered | H62: 60
A63: DEL00062 | B63: ORD00062 | C63: 45396 | D63: 45399 | F63: Delhivery | G63: Cancelled | H63: 80
A64: DEL00063 | B64: ORD00063 | C64: 45542 | D64: 45545 | E64: 45545 | F64: BlueDart | G64: Delivered | H64: 60
A65: DEL00064 | B65: ORD00064 | C65: 45757 | D65: 45759 | E65: 45759 | F65: XpressBees | G65: Delivered | H65: 60
A66: DEL00065 | B66: ORD00065 | C66: 45845 | D66: 45847 | E66: 45847 | F66: Delhivery | G66: Delivered | H66: 60
A67: DEL00066 | B67: ORD00066 | C67: 45878 | D67: 45880 | E67: 45880 | F67: Shiprocket | G67: Delivered | H67: 100
A68: DEL00067 | B68: ORD00067 | C68: 45644 | D68: 45647 | F68: BlueDart | G68: Cancelled | H68: 80
A69: DEL00068 | B69: ORD00068 | C69: 45866 | D69: 45868 | E69: 45869 | F69: Ecom Express | G69: Delayed | H69: 60
A70: DEL00069 | B70: ORD00069 | C70: 45393 | D70: 45395 | E70: 45396 | F70: BlueDart | G70: Delayed | H70: 80
A71: DEL00070 | B71: ORD00070 | C71: 45318 | D71: 45321 | F71: Delhivery | G71: Cancelled | H71: 45
A72: DEL00071 | B72: ORD00071 | C72: 45314 | D72: 45316 | E72: 45317 | F72: Ecom Express | G72: Delayed | H72: 50
A73: DEL00072 | B73: ORD00072 | C73: 45365 | D73: 45368 | E73: 45368 | F73: BlueDart | G73: Delivered | H73: 70
A74: DEL00073 | B74: ORD00073 | C74: 45846 | D74: 45850 | E74: 45850 | F74: XpressBees | G74: Delivered | H74: 60
A75: DEL00074 | B75: ORD00074 | C75: 45756 | D75: 45758 | E75: 45759 | F75: Delhivery | G75: Delayed | H75: 70
A76: DEL00075 | B76: ORD00075 | C76: 45937 | D76: 45939 | F76: Shiprocket | G76: Cancelled | H76: 45
A77: DEL00076 | B77: ORD00076 | C77: 45414 | D77: 45416 | E77: 45417 | F77: BlueDart | G77: Delayed | H77: 100
A78: DEL00077 | B78: ORD00077 | C78: 45323 | D78: 45327 | E78: 45327 | F78: BlueDart | G78: Delivered | H78: 60
A79: DEL00078 | B79: ORD00078 | C79: 45540 | D79: 45544 | F79: XpressBees | G79: Cancelled | H79: 60
A80: DEL00079 | B80: ORD00079 | C80: 45314 | D80: 45316 | E80: 45316 | F80: BlueDart | G80: Delivered | H80: 100
A81: DEL00080 | B81: ORD00080 | C81: 45946 | D81: 45948 | E81: 45948 | F81: XpressBees | G81: Delivered | H81: 60
A82: DEL00081 | B82: ORD00081 | C82: 45515 | D82: 45518 | E82: 45518 | F82: Shiprocket | G82: Delivered | H82: 55
A83: DEL00082 | B83: ORD00082 | C83: 45297 | D83: 45301 | E83: 45301 | F83: XpressBees | G83: Delivered | H83: 100
A84: DEL00083 | B84: ORD00083 | C84: 45775 | D84: 45780 | E84: 45780 | F84: XpressBees | G84: Delivered | H84: 80
A85: DEL00084 | B85: ORD00084 | C85: 45737 | D85: 45740 | E85: 45741 | F85: BlueDart | G85: Delayed | H85: 80
A86: DEL00085 | B86: ORD00085 | C86: 45332 | D86: 45335 | E86: 45335 | F86: XpressBees | G86: Delivered | H86: 70
A87: DEL00086 | B87: ORD00086 | C87: 45457 | D87: 45462 | F87: Delhivery | G87: Cancelled | H87: 100
A88: DEL00087 | B88: ORD00087 | C88: 45486 | D88: 45488 | E88: 45489 | F88: Ecom Express | G88: Delayed | H88: 50
A89: DEL00088 | B89: ORD00088 | C89: 45776 | D89: 45781 | E89: 45782 | F89: Delhivery | G89: Delayed | H89: 55
A90: DEL00089 | B90: ORD00089 | C90: 45701 | D90: 45704 | E90: 45704 | F90: XpressBees | G90: Delivered | H90: 80
A91: DEL00090 | B91: ORD00090 | C91: 45503 | D91: 45508 | E91: 45510 | F91: Ecom Express | G91: Delayed | H91: 60
A92: DEL00091 | B92: ORD00091 | C92: 45702 | D92: 45705 | E92: 45705 | F92: Delhivery | G92: Delivered | H92: 45
A93: DEL00092 | B93: ORD00092 | C93: 45526 | D93: 45528 | E93: 45528 | F93: Ecom Express | G93: Delivered | H93: 70
A94: DEL00093 | B94: ORD00093 | C94: 45719 | D94: 45723 | F94: Ecom Express | G94: Cancelled | H94: 50
A95: DEL00094 | B95: ORD00094 | C95: 45777 | D95: 45781 | E95: 45781 | F95: XpressBees | G95: Delivered | H95: 70
A96: DEL00095 | B96: ORD00095 | C96: 45450 | D96: 45454 | F96: XpressBees | G96: Cancelled | H96: 60
A97: DEL00096 | B97: ORD00096 | C97: 45627 | D97: 45630 | E97: 45630 | F97: XpressBees | G97: Delivered | H97: 50
A98: DEL00097 | B98: ORD00097 | C98: 45925 | D98: 45927 | E98: 45928 | F98: Delhivery | G98: Delayed | H98: 60
A99: DEL00098 | B99: ORD00098 | C99: 45904 | D99: 45908 | E99: 45908 | F99: Delhivery | G99: Delivered | H99: 100
A100: DEL00099 | B100: ORD00099 | C100: 45439 | D100: 45444 | E100: 45444 | F100: BlueDart | G100: Delivered | H100: 50
...

Sheet Marketing
A1: Campaign_ID | B1: Campaign_Name | C1: Marketing_Channel | D1: Start_Date | E1: End_Date | F1: Campaign_Budget | G1: Amount_Spent
A2: CAMP001 | B2: Republic Day Sale | C2: Influencer | D2: 45306 | E2: 45318 | F2: 75000 | G2: 69243
A3: CAMP002 | B3: Valentine Flash Sale | C3: Google Ads | D3: 45338 | E3: 45354 | F3: 75000 | G3: 59657
A4: CAMP003 | B4: Holi Savings | C4: Facebook | D4: 45370 | E4: 45377 | F4: 25000 | G4: 18398
A5: CAMP004 | B5: Summer Kickoff | C5: Facebook | D5: 45402 | E5: 45414 | F5: 60000 | G5: 57395
A6: CAMP005 | B6: Monsoon Deals | C6: Influencer | D6: 45434 | E6: 45443 | F6: 40000 | G6: 38346
A7: CAMP006 | B7: Independence Day Sale | C7: Instagram | D7: 45466 | E7: 45477 | F7: 50000 | G7: 37955
A8: CAMP007 | B8: Raksha Bandhan Offers | C8: Google Ads | D8: 45498 | E8: 45510 | F8: 40000 | G8: 35656
A9: CAMP008 | B9: Festive Preview | C9: Affiliate | D9: 45530 | E9: 45551 | F9: 50000 | G9: 38090
A10: CAMP009 | B10: Diwali Mega Sale | C10: Facebook | D10: 45562 | E10: 45571 | F10: 75000 | G10: 64017
A11: CAMP010 | B11: Black Friday Deals | C11: Email | D11: 45594 | E11: 45613 | F11: 60000 | G11: 51873
A12: CAMP011 | B12: Year End Clearance | C12: Affiliate | D12: 45626 | E12: 45644 | F12: 50000 | G12: 39110
A13: CAMP012 | B13: New Year Kickoff | C13: Facebook | D13: 45658 | E13: 45668 | F13: 25000 | G13: 23636
... A21: CAMP020 | B21: Mega Savings Week | C21: Facebook | D21: 45915 | E21: 45927 | F21: 90000 | G21: 75535

Sheet Reviews
A1: Review_ID | B1: Order_ID | C1: Customer_ID | D1: Product_ID | E1: Rating | F1: Review_Date | G1: Review_Text
A2: REV0001 | B2: ORD00587 | C2: CUST1131 | D2: P057 | E2: 4 | F2: 45731 | G2: Happy with the purchase
A3: REV0002 | B3: ORD01254 | C3: CUST0152 | D3: P002 | E3: 5 | F3: 45404 | G3: Very satisfied
A4: REV0003 | B4: ORD00826 | C4: CUST0867 | D4: P002 | E4: 4 | F4: 45901 | G4: Good quality and service
A5: REV0004 | B5: ORD00181 | C5: CUST0145 | D5: P077 | E5: 5 | F5: 45676 | G5: Great experience
A6: REV0005 | B6: ORD01077 | C6: CUST0072 | D6: P026 | E6: 4 | F6: 45414 | G6: Good product
A7: REV0006 | B7: ORD00690 | C7: CUST0647 | D7: P065 | E7: 3 | F7: 45907 | G7: It was fine
A8: REV0007 | B8: ORD00288 | C8: CUST0534 | D8: P066 | E8: 5 | F8: 45815 | G8: Very satisfied
A9: REV0008 | B9: ORD00926 | C9: CUST1180 | D9: P028 | E9: 1 | F9: 45583 | G9: Very disappointing
A10: REV0009 | B10: ORD02418 | C10: CUST0650 | D10: P037 | E10: 4 | F10: 45306 | G10: Good quality and service
A11: REV0010 | B11: ORD01531 | C11: CUST0264 | D11: P079 | E11: 4 | F11: 45447 | G11: Happy with the purchase
A12: REV0011 | B12: ORD00832 | C12: CUST0615 | D12: P030 | E12: 3 | F12: 45897 | G12: It was fine
A13: REV0012 | B13: ORD02277 | C13: CUST1193 | D13: P056 | E13: 4 | F13: 45736 | G13: Happy with the purchase
... A1501: REV1500 | B1501: ORD02004 | C1501: CUST0402 | D1501: P095 | E1501: 4 | F1501: 45417 | G1501: Good product
